django_prerenderio/__init__.py
django_prerenderio/middleware.py
django_prerenderio-17.6.1.dist-info/DESCRIPTION.rst
django_prerenderio-17.6.1.dist-info/METADATA
django_prerenderio-17.6.1.dist-info/RECORD
django_prerenderio-17.6.1.dist-info/WHEEL
django_prerenderio-17.6.1.dist-info/metadata.json
django_prerenderio-17.6.1.dist-info/top_level.txt
