Metadata-Version: 2.0
Name: django-prerenderio
Version: 17.6.1
Summary: Django middleware to render Single Page Applications via prerender.io
Home-page: https://github.com/pizzapanther/pizzapanther.github.io/tree/master/libs/django-prerenderio
Author: Paul Bailey
Author-email: paul@neutrondrive.com
License: MIT
Keywords: django prerender prerender.io seo spa angular react vuejs
Platform: any
Requires-Dist: requests
